{
  "en": {
    "items": {
      "item_none": {
        "Name": "None",
        "TypeItem": "",
        "Quality": "",
        "Description": ""
      },
      "sword_gods_slayer": {
        "Name": "Gods Slayer",
        "TypeItem": "",
        "Quality": "",
        "Description": "Good sword"
      },
      "gun_makarov": {
        "Name": "Makarov pistol",
        "TypeItem": "",
        "Quality": "",
        "Description": "Just simple pistol"
      },
      "item_meat": {
        "Name": "Meat",
        "TypeItem": "",
        "Quality": "",
        "Description": "Tasty meat"
      },
      "item_potion_hp": {
        "Name": "HP Potion",
        "TypeItem": "",
        "Quality": "",
        "Description": "Heals 10 HP"
      },
      "armor_armor": {
        "Name": "Base armor",
        "TypeItem": "",
        "Quality": "",
        "Description": "Add +2 armor"
      },
      "minion_robot_es": {
        "Name": "Robo Minion",
        "TypeItem": "",
        "Quality": "",
        "Description": "This minion allows you to disassemble tech creatures into tech components."
      },
      "material_chip_one": {
        "Name": "Chip TTA",
        "TypeItem": "",
        "Quality": "",
        "Description": "Basic chip"
      },
      "material_gear_one": {
        "Name": "Gear T006",
        "TypeItem": "",
        "Quality": "",
        "Description": "Simple gear"
      },
      "material_dif_parts_one": {
        "Name": "Different part TH",
        "TypeItem": "",
        "Quality": "",
        "Description": "Rare different part TH"
      },
      "sword_parts_one": {
        "Name": "Sword part",
        "TypeItem": "",
        "Quality": "",
        "Description": "A part of a sabre"
      },
      "bow_parts_one": {
        "Name": "Bow part",
        "TypeItem": "",
        "Quality": "",
        "Description": "A part of a simple bow"
      },
      "trap_mine": {
        "Name": "Mine",
        "TypeItem": "",
        "Quality": "",
        "Description": "This mine damages nearby enemies"
      },
      "bow_simple": {
        "Name": "Simple bow",
        "TypeItem": "",
        "Quality": "",
        "Description": "A long-range bow"
      },
      "shotgun_pump": {
        "Name": "Pump Shotgun",
        "TypeItem": "",
        "Quality": "",
        "Description": "A powerful shotgun effective at close range, dealing heavy damage to groups of enemies."
      },
      "minion_mage_es": {
        "Name": "Mage minion",
        "TypeItem": "",
        "Quality": "",
        "Description": "This minion allows you to disassemble magical creatures into artifacts."
      },
      "minion_mixed_es": {
        "Name": "Universal Minion",
        "TypeItem": "",
        "Quality": "",
        "Description": "This very rare minion allows you to disassemble all creatures."
      },
      "soldier_spear": {
        "Name": "Soldier's spear",
        "TypeItem": "",
        "Quality": "",
        "Description": "A decent soldier's spear."
      },
      "simple_knife": {
        "Name": "Simple knife",
        "TypeItem": "",
        "Quality": "",
        "Description": "A small simple knife"
      },
      "item_potion_speed": {
        "Name": "Slime Speed ​​Potion",
        "TypeItem": "",
        "Quality": "",
        "Description": "A simple yet effective speed potion."
      },
      "material_iron_bar": {
        "Name": "Iron bar",
        "TypeItem": "",
        "Quality": "",
        "Description": "A strong and durable piece of iron bar, useful for crafting and forging."
      },
      "axe_woodcutter": {
        "Name": "Woodcutter's Axe",
        "TypeItem": "",
        "Quality": "",
        "Description": "A sturdy axe used by woodcutters to chop down trees efficiently."
      },
      "material_wood": {
        "Name": "Wood",
        "TypeItem": "",
        "Quality": "",
        "Description": "A basic material used in crafting."
      },
      "material_bottle": {
        "Name": "Bottle",
        "TypeItem": "",
        "Quality": "",
        "Description": "A simple glass bottle, essential for potion-making."
      },
      "material_sunflower": {
        "Name": "Sunflower",
        "TypeItem": "",
        "Quality": "",
        "Description": "A bright flower infused with a trace of solar energy. Used in alchemy."
      },
      "material_rubin": {
        "Name": "Ruby",
        "TypeItem": "",
        "Quality": "",
        "Description": "A precious gemstone of deep red color, used in crafting, magic, and alchemy."
      },
      "material_rubin_piece": {
        "Name": "Ruby Shard",
        "TypeItem": "",
        "Quality": "",
        "Description": "A piece of ruby, essential for potion brewing and accessory crafting."
      },
      "material_glass": {
        "Name": "Glass",
        "TypeItem": "",
        "Quality": "",
        "Description": "A transparent material used in crafting and alchemy."
      },
      "material_someone_eye": {
        "Name": "Someone's Eye",
        "TypeItem": "",
        "Quality": "",
        "Description": "A strange eye, its owner unknown."
      },
      "material_strange_eye": {
        "Name": "Strange Eye",
        "TypeItem": "",
        "Quality": "",
        "Description": "An eye with a mystical aura."
      },
      "artifact_simple_ring": {
        "Name": "Simple Ring",
        "TypeItem": "",
        "Quality": "",
        "Description": "A plain ring with no visible power. Still, it might hold hidden potential."
      },
      "artifact_eye_ring": {
        "Name": "Eye Ring",
        "TypeItem": "",
        "Quality": "",
        "Description": "A mysterious ring with an embedded eye. It seems to watch your every move."
      },
      "material_tooth_mimic": {
        "Name": "Mimic Tooth",
        "TypeItem": "",
        "Quality": "",
        "Description": "A jagged tooth torn from a mimic. Still drips with slime and menace."
      },
      "material_tongue_mimic": {
        "Name": "Mimic Tongue",
        "TypeItem": "",
        "Quality": "",
        "Description": "The squirming tongue of a mimic. It occasionally twitches as if still alive."
      },
      "material_bur": {
        "Name": "Drill",
        "TypeItem": "",
        "Quality": "",
        "Description": "A worn-out drill that can still pierce through rock. It radiates mechanical power."
      },
      "material_wheel": {
        "Name": "Wheel",
        "TypeItem": "",
        "Quality": "",
        "Description": "A sturdy wheel that once spun at wild speeds. Now it waits for a new machine."
      },
      "material_battery": {
        "Name": "Battery",
        "TypeItem": "",
        "Quality": "",
        "Description": "A mystical battery filled with unstable energy. It hums even when not connected."
      },
      "material_fast_engine": {
        "Name": "Fast Engine",
        "TypeItem": "",
        "Quality": "",
        "Description": "A legendary engine built for speed. Starting it up sounds like thunder roaring."
      },
      "material_saw_blade": {
        "Name": "Saw Blade",
        "TypeItem": "",
        "Quality": "",
        "Description": "A toothed blade that leaves only dust and splinters behind. Sharp and dangerous."
      },
      "material_copper_wires": {
        "Name": "Copper Wires",
        "TypeItem": "",
        "Quality": "",
        "Description": "Ordinary copper wires. Flexible, reliable, still fit for conducting energy."
      },
      "material_lamp": {
        "Name": "Lamp",
        "TypeItem": "",
        "Quality": "",
        "Description": "A rare lamp that emits a gentle light. As if it illuminates not only the path but also the mind."
      },
      "material_wings_fly": {
        "Name": "Gluttonwing Wings",
        "TypeItem": "",
        "Quality": "",
        "Description": "Wings torn from the Gluttonwing — a ravenous flying creature. They carry the scent of food."
      },
      "material_simple_engine": {
        "Name": "Simple Engine",
        "TypeItem": "",
        "Quality": "",
        "Description": "A simple but reliable engine. It doesn’t shine, but it always gets the job done."
      },
      "pickaxe_simple": {
        "Name": "Simple Pickaxe",
        "TypeItem": "Weapon",
        "Quality": "Rare",
        "Description": "A basic yet reliable pickaxe. Well-suited for mining ores and minerals."
      },
      "bur_t0k6": {
        "Name": "Drill T0-K6",
        "TypeItem": "Weapon",
        "Quality": "Mystical",
        "Description": "A powerful drill designed for fast and deep mining. Significantly more efficient than a pickaxe, especially on hard surfaces."
      },
      "material_slime_acid": {
        "Name": "Slime Acid",
        "TypeItem": "Material",
        "Quality": "Common",
        "Description": "A corrosive fluid secreted by slimes. Used to dissolve tough minerals like quartzite."
      },
      "material_quartzite": {
        "Name": "Quartzite",
        "TypeItem": "Material",
        "Quality": "Common",
        "Description": "A hard mineral that can be dissolved with slime acid to obtain quartz sand."
      },
      "material_quartz_sand": {
        "Name": "Quartz Sand",
        "TypeItem": "Material",
        "Quality": "Common",
        "Description": "Fine sand obtained from quartzite. Can be smelted into durable and pure glass."
      },
      "material_iron_ore": {
        "Name": "Iron Ore",
        "TypeItem": "Material",
        "Quality": "Common",
        "Description": "A heavy, dense ore that can be smelted into iron ingots."
      },
      "staff_forest": {
        "Name": "Forest Staff",
        "TypeItem": "Staff",
        "Quality": "Rare",
        "Description": "A magical staff imbued with the essence of the forest. Its strikes unleash bursts of natural energy that bend foes to nature’s will."
      },
      "trap_foottrap": {
        "Name": "Contact Trap",
        "TypeItem": "Trap",
        "Quality": "Uncommon",
        "Description": "Activates upon surface contact. Reliably halts ground-based targets — from living creatures to machines and mechanisms."
      },
      "item_force_air": {
        "Name": "Essence of Flight",
        "TypeItem": "Consumable",
        "Quality": "Uncommon",
        "Description": "A vessel containing sealed flight energy. Releases a strong impulse when activated, briefly propelling or pushing the user."
      },
      "material_beetle_shell": {
        "Name": "Beetle Shell",
        "TypeItem": "Material",
        "Quality": "Uncommon",
        "Description": "A sturdy, smooth fragment of shell harvested from the Skullroller and Field Beetle. Currently has no use, but shows great potential."
      },
      "material_beetle_sludge": {
        "Name": "Beetle Sludge",
        "TypeItem": "Material",
        "Quality": "Common",
        "Description": "A sticky substance left behind by magical beetles. Used as an organic adhesive in contact-based traps."
      },
      "seed_sunflower": {
        "Name": "Sunflower Seed",
        "TypeItem": "",
        "Quality": "",
        "Description": "Seed of a bright sunflower. Used in alchemy and gardening."
      },
      "seed_tallsha": {
        "Name": "Tallsha Seed",
        "TypeItem": "",
        "Quality": "",
        "Description": "Seed of the Tallsha plant. Grows quickly and is used in crafting and alchemy."
      },
      "seed_tonalia": {
        "Name": "Tonalia Seed",
        "TypeItem": "",
        "Quality": "",
        "Description": "Seed of the elegant Tonalia flower. Valued for its magical petals."
      },
      "material_tolania_leaves": {
        "Name": "Tolania Leaves",
        "TypeItem": "",
        "Quality": "",
        "Description": "Fragrant leaves of the rare Tolania plant. Used in alchemy and medicine."
      },
      "material_tallsha": {
        "Name": "Tallsha",
        "TypeItem": "",
        "Quality": "",
        "Description": "A tall, dense plant resembling dry brush. Commonly used in potion brewing and crafting."
      },
      "item_potion_mana": {
        "Name": "Mana Potion",
        "TypeItem": "Potion",
        "Quality": "Uncommon",
        "Description": "A murky blue-violet liquid, concentrated magical energy. Restores mana when consumed."
      },
      "item_moonana": {
        "Name": "Moonana",
        "TypeItem": "Food",
        "Quality": "Uncommon",
        "Description": "A rare lunar fruit that glows in the dark. Sweet and juicy, it restores health and a bit of mana."
      },
      "item_pepper": {
        "Name": "Hot Pepper",
        "TypeItem": "Food",
        "Quality": "Common",
        "Description": "Small but extremely spicy. Used in cooking and alchemy to craft enhanced meals."
      },
      "item_spicy_meat": {
        "Name": "Spicy Meat",
        "TypeItem": "Food",
        "Quality": "Uncommon",
        "Description": "A dish made from meat, pepper, and tallsha. Fills you with energy, restores health, and warms you up from within."
      },
      "minion_gunmin_tech": {
        "Name": "Tech-Tar Minion",
        "TypeItem": "",
        "Quality": "",
        "Description": "This minion attacks enemies and temporarily immobilizes them."
      },
      "minion_heal": {
        "Name": "Healing Minion",
        "TypeItem": "",
        "Quality": "",
        "Description": "This minion heals the player, restoring health during combat."
      },
      "lazergun_tra": {
        "Name": "Laser-TRA2000",
        "TypeItem": "Weapon",
        "Quality": "Legendary",
        "Description": "The flagship weapon of the TRA series. Fires a powerful piercing laser beam that vaporizes enemies in seconds. Reliability, power, and style in one sleek package."
      },
      "thunder_gun": {
        "Name": "Thunder Blaster",
        "TypeItem": "Weapon",
        "Quality": "Mystical",
        "Description": "A gun that fires chaining lightning bolts, bouncing from one enemy to another. Perfect for dealing with groups — electricity always finds a way."
      },
      "thunder_stuff": {
        "Name": "Storm Staff",
        "TypeItem": "Weapon",
        "Quality": "Mystical",
        "Description": "A magical staff that unleashes chaining lightning bolts, jumping between enemies. Consumes mana and excels at battling multiple foes at once."
      },
      "material_book": {
        "Name": "Book of Knowledge",
        "TypeItem": "Material",
        "Quality": "Common",
        "Description": "A simple book filled with basic notes. Used in crafting and research."
      },
      "booster_intelligence": {
        "Name": "Tome of Intelligence",
        "TypeItem": "Material",
        "Quality": "Rare",
        "Description": "An ancient tome covered in arcane symbols. Increases intelligence by 2 when used."
      },
      "material_syringe": {
        "Name": "Empty Syringe",
        "TypeItem": "Material",
        "Quality": "Common",
        "Description": "A standard sterile syringe. Used for crafting various enhancement injectors."
      },
      "booster_strength": {
        "Name": "Strength Booster Syringe",
        "TypeItem": "Material",
        "Quality": "Rare",
        "Description": "A syringe filled with a concentrated stimulant. Increases strength by 2."
      },
      "booster_agillity": {
        "Name": "Agility Booster Syringe",
        "TypeItem": "Material",
        "Quality": "Rare",
        "Description": "A syringe containing a fast-acting formula. Increases agility by 2."
      }
    },
    "mobs": {
      "daizen_enem": {
        "Name": "Daizen",
        "TypeMob": "",
        "Description": "Just melee mob"
      },
      "rainger_enem": {
        "Name": "Rainger",
        "TypeMob": "",
        "Description": "Just ranger mob"
      },
      "slime_enem": {
        "Name": "Slime",
        "TypeMob": "",
        "Description": "Medium slime"
      },
      "slime_boss_enem": {
        "Name": "Big Damn Slime",
        "TypeMob": "",
        "Description": "This is a really big damn slime, no joke!"
      },
      "mimic_enem": {
        "Name": "Mimic Chest",
        "TypeMob": "",
        "Description": "A fast and dangerous chest"
      },
      "death_car_enem": {
        "Name": "Death Machine",
        "TypeMob": "",
        "Description": "A robotic car with a circular saw, built to exterminate all life in its path"
      },
      "tasty_fly_enem": {
        "Name": "Gluttonwing",
        "TypeMob": "",
        "Description": "A green winged creature with nothing but a mouth and a great sense of smell. Loves to gobble up anything it can find."
      },
      "bur_enem": {
        "Name": "Cave Ripper",
        "TypeMob": "",
        "Description": "A relentless drilling machine built for tunnels, tearing through stone and flesh alike as it carves its endless path through the caves."
      },
      "bug_skull_enem": {
        "Name": "Skullroller",
        "TypeMob": "",
        "Description": "A strange beetle from a magical realm that rolls a giant skull of an ancient titan. It hurls the skull at enemies with crushing force."
      },
      "bug_enem": {
        "Name": "Field Beetle",
        "TypeMob": "",
        "Description": "A small but fast beetle from enchanted lands. Without its deadly skull, it charges straight at its target with raw momentum."
      }
    },
    "ui_text": {
      "player_stats_name": {
        "word_status_info": "Status info",
        "word_Cur_Hp": "Current HP",
        "word_Max_Hp": "Maximum HP",
        "word_Max_Mana": "Max Mana",
        "word_Mana": "Mana",
        "word_Mana_Regen": "To Mana Regen",
        "word_Armor_Hp": "Armor",
        "word_Mov_Speed": "Move speed",
        "word_Att_Range": "Bonus attack range",
        "word_Att_Damage": "Bonus damage",
        "word_Att_Speed": "Bonus attack speed",
        "word_Proj_Speed": "Bonus projectile speed",
        "word_level": "Level",
        "word_freeSkillPoints": "Free skill points",
        "word_cur_exp": "Current exp",
        "word_nextLvl_exp": "To the next level",
        "word_classPlayer": "Class player",
        "word_curse_lvl": "Curse level",
        "word_char_lvl": "Enchantment level",
        "word_art_lvl": "Artifact level",
        "word_Damage": "Damage",
        "word_Armor": "Armor",
        "word_Speed": "Speed",
        "word_Evasion": "Evasion",
        "word_AttSpeed": "Att.speed",
        "word_AttRange": "Att.range",
        "word_ProjSpeed": "Proj.speed",
        "word_eqipment": "equip",
        "word_roleClass": "class",
        "word_strength": "str",
        "word_agility": "agil",
        "word_intelligence": "int",
        "word_expBonus": "exp bonus",
        "word_base": "base",
        "word_for": "for ",
        "word_TradeSkill": "Trade skill",
        "word_gold": "Gold",
        "word_technology_gold": "Technology points",
        "word_mage_gold": "Magic points",
        "word_count_proj": "Bonus count projectiles",
        "word_Tech_Resis": "Tech Resist",
        "word_Magic_Resis": "Magic Resist",
        "word_trade_skill": "Trade",
        "word_farm_skill": "Farming",
        "word_collect_skill": "Collecting",
        "word_experience": "experience",
        "word_exp_to_next_level": "experience to next level"
      },
      "slots_name": {
        "word_player": "player",
        "word_typeItem": "Item type",
        "word_damageType": "Damage type",
        "word_damage": "Damage per attack",
        "word_attacks_speed": "Attack speed",
        "word_attacks_intervals": "Attacks per second",
        "word_range": "Range",
        "word_manaCost": "Mana Cost",
        "word_description": "Description"
      },
      "shop_text": {
        "word_gold": "gold",
        "word_not_enough_money": "Not enough gold",
        "word_total_value": "Total value: ",
        "word_personal_cost": "Personal cost: ",
        "word_trade_without_gold": "Trading without gold",
        "word_must_pay": "You must pay",
        "word_will_receive": "You will receive",
        "word_your_gold": "Your gold: ",
        "word_your_trade_skill": "Your trading skill: ",
        "word_cost": "Cost: ",
        "word_trade_success": "Trade successful",
        "word_player": "Player",
        "word_trader": "Trader",
        "word_trade_name": "Trade"
      },
      "aspects_name": {
        "word_nameWindow": "Choose an Upgrade",
        "word_acceptButton": "Select",
        "word_Agillity": "to Agility",
        "word_Strength": "to Strength",
        "word_Intelligence": "to Intelligence",
        "word_Tech_Point": "to Tech Points",
        "word_Mage_Point": "to Mage Points",
        "word_Exp_Bust": "to EXP Boost",
        "word_Speed": "to Speed",
        "word_Hp": "to Health Points",
        "word_Mana": "to mana points",
        "word_Mana_Regen": "to Mana Regen",
        "word_Gold": "to Gold",
        "word_AttackSpeed": "to Attack Speed",
        "word_Range": "to Range",
        "word_Projectile_speed": "to Projectile Speed",
        "word_Damage": "to damage"
      },
      "name_location": {
        "Game_village": "Village of Tonio the almost wise",
        "Level_one": "Level №1 Field of slightly angry sheep",
        "Level_two": "Level №2 Shadowfang Hollow"
      }
    }
  },
  "ru": {
    "items": {
      "item_none": {
        "Name": "Ничего",
        "TypeItem": "",
        "Quality": "",
        "Description": ""
      },
      "sword_gods_slayer": {
        "Name": "Убийца Богов",
        "TypeItem": "",
        "Quality": "",
        "Description": "Хороший меч"
      },
      "gun_makarov": {
        "Name": "Пистолет Макаров",
        "TypeItem": "",
        "Quality": "",
        "Description": "Обычный пистолет"
      },
      "item_meat": {
        "Name": "Мясо",
        "TypeItem": "",
        "Quality": "",
        "Description": "Вкусное мяско"
      },
      "item_potion_hp": {
        "Name": "Зелье здоровья",
        "TypeItem": "",
        "Quality": "",
        "Description": "Восстанавливает 10 хп"
      },
      "armor_armor": {
        "Name": "Обычная броня",
        "TypeItem": "",
        "Quality": "",
        "Description": "Даёт +2 к броне"
      },
      "minion_robot_es": {
        "Name": "Робо-миньон",
        "TypeItem": "",
        "Quality": "",
        "Description": "Этот миньон позволяет разбирать технических существ на технологические компоненты."
      },
      "material_chip_one": {
        "Name": "Чип TTA",
        "TypeItem": "",
        "Quality": "",
        "Description": "Простой чип"
      },
      "material_gear_one": {
        "Name": "Шестерня T006",
        "TypeItem": "",
        "Quality": "",
        "Description": "Простая шестерня"
      },
      "material_dif_parts_one": {
        "Name": "Разные части TH",
        "TypeItem": "",
        "Quality": "",
        "Description": "Редкие разные части TH"
      },
      "sword_parts_one": {
        "Name": "Части от меча",
        "TypeItem": "",
        "Quality": "",
        "Description": "Разные части к простой сабли"
      },
      "bow_parts_one": {
        "Name": "Части к луку",
        "TypeItem": "",
        "Quality": "",
        "Description": "Части к простому луку"
      },
      "trap_mine": {
        "Name": "Мина",
        "TypeItem": "",
        "Quality": "",
        "Description": "Эта мина делает больно окружающим"
      },
      "bow_simple": {
        "Name": "Простой лук",
        "TypeItem": "",
        "Quality": "",
        "Description": "Лук для дальней дистанции"
      },
      "shotgun_pump": {
        "Name": "Помповый дробовик",
        "TypeItem": "",
        "Quality": "",
        "Description": "Много снарядов разорвут большую ближнюю цель или толпу"
      },
      "minion_mage_es": {
        "Name": "Магический миньон",
        "TypeItem": "",
        "Quality": "",
        "Description": "Этот миньон позволяет разбирать магических существ на артефакты"
      },
      "minion_mixed_es": {
        "Name": "Универсальный миньон",
        "TypeItem": "",
        "Quality": "",
        "Description": "Этот очень редкий миньон позволяет разбирать всех существ."
      },
      "soldier_spear": {
        "Name": "Солдатское копьё",
        "TypeItem": "",
        "Quality": "",
        "Description": "Неплохое солдатское копьё."
      },
      "simple_knife": {
        "Name": "Простой ножик",
        "TypeItem": "",
        "Quality": "",
        "Description": "Маленький простой ножик"
      },
      "item_potion_speed": {
        "Name": "Слизневое зелье скорости",
        "TypeItem": "",
        "Quality": "",
        "Description": "Простое, но эффективное зелье скорости"
      },
      "material_iron_bar": {
        "Name": "Железный слиток",
        "TypeItem": "",
        "Quality": "",
        "Description": "Прочный и долговечный кусок железного слиток, полезный для ремесла и ковки."
      },
      "axe_woodcutter": {
        "Name": "Топор дровосека",
        "TypeItem": "",
        "Quality": "",
        "Description": "Прочный топор, которым дровосеки эффективно рубят деревья."
      },
      "material_wood": {
        "Name": "Дерево",
        "TypeItem": "",
        "Quality": "",
        "Description": "Основной материал, используемый в ремесле."
      },
      "material_bottle": {
        "Name": "Бутылка",
        "TypeItem": "",
        "Quality": "",
        "Description": "Простая стеклянная бутылка, необходимая для создания зелий."
      },
      "material_sunflower": {
        "Name": "Подсолнух",
        "TypeItem": "",
        "Quality": "",
        "Description": "Яркий цветок с частицей солнечной энергии. Используется в алхимии."
      },
      "material_rubin": {
        "Name": "Рубин",
        "TypeItem": "",
        "Quality": "",
        "Description": "Драгоценный камень насыщенного красного цвета, применяемый в ремесле, магии и алхимии."
      },
      "material_rubin_piece": {
        "Name": "Осколок рубина",
        "TypeItem": "",
        "Quality": "",
        "Description": "Кусок рубина, необходимый для зельеварения и создания аксессуаров."
      },
      "material_glass": {
        "Name": "Стекло",
        "TypeItem": "",
        "Quality": "",
        "Description": "Прозрачный материал, используемый в ремесле и алхимии."
      },
      "material_someone_eye": {
        "Name": "Чей-то глаз",
        "TypeItem": "",
        "Quality": "",
        "Description": "Странный глаз, неизвестно кому принадлежащий."
      },
      "material_strange_eye": {
        "Name": "Странный глаз",
        "TypeItem": "",
        "Quality": "",
        "Description": "Глаз с мистической аурой."
      },
      "artifact_simple_ring": {
        "Name": "Простое Кольцо",
        "TypeItem": "",
        "Quality": "",
        "Description": "Простое кольцо без видимой силы. Тем не менее, возможно, в нём скрыт потенциал."
      },
      "artifact_eye_ring": {
        "Name": "Кольцо с Глазом",
        "TypeItem": "",
        "Quality": "",
        "Description": "Загадочное кольцо с вкраплённым глазом. Кажется, оно следит за каждым твоим движением."
      },
      "material_tooth_mimic": {
        "Name": "Зуб мимика",
        "TypeItem": "",
        "Quality": "",
        "Description": "Оскалённый зуб, вырванный из пасти мимика. Всё ещё покрыт слизью и злобой."
      },
      "material_tongue_mimic": {
        "Name": "Язык мимика",
        "TypeItem": "",
        "Quality": "",
        "Description": "Извивающийся язык мимика. Порой вздрагивает, будто всё ещё живой."
      },
      "material_bur": {
        "Name": "Бур",
        "TypeItem": "",
        "Quality": "",
        "Description": "Изношенный бур, всё ещё способный пробурить скалу. В нём чувствуется механическая мощь."
      },
      "material_wheel": {
        "Name": "Колесо",
        "TypeItem": "",
        "Quality": "",
        "Description": "Прочное колесо, когда-то вращавшееся с бешеной скоростью. Теперь оно ждёт новой машины."
      },
      "material_battery": {
        "Name": "Батарея",
        "TypeItem": "",
        "Quality": "",
        "Description": "Мистическая батарея, наполненная нестабильной энергией. Гудит, даже когда не подключена."
      },
      "material_fast_engine": {
        "Name": "Быстрый двигатель",
        "TypeItem": "",
        "Quality": "",
        "Description": "Легендарный двигатель, созданный для скорости. Его запуск — это рёв грома."
      },
      "material_saw_blade": {
        "Name": "Пильный диск",
        "TypeItem": "",
        "Quality": "",
        "Description": "Зубчатый диск, оставляющий после себя лишь пыль и стружку. Острый и опасный."
      },
      "material_copper_wires": {
        "Name": "Медные провода",
        "TypeItem": "",
        "Quality": "",
        "Description": "Обычные медные провода. Гибкие, надёжные, всё ещё пригодны для проводки энергии."
      },
      "material_lamp": {
        "Name": "Лампа",
        "TypeItem": "",
        "Quality": "",
        "Description": "Редкая лампа, излучающая мягкий свет. Будто освещает не только путь, но и мысли."
      },
      "material_wings_fly": {
        "Name": "Крылья Обжирокрыла",
        "TypeItem": "",
        "Quality": "",
        "Description": "Крылья, сорванные с Обжирокрыла — прожорливого крылатого существа. Источают аромат пищи."
      },
      "material_simple_engine": {
        "Name": "Простой двигатель",
        "TypeItem": "",
        "Quality": "",
        "Description": "Простой, но надёжный двигатель. Не сверкает, но всегда выполняет свою работу."
      },
      "pickaxe_simple": {
        "Name": "Простая кирка",
        "TypeItem": "Оружие",
        "Quality": "Редкое",
        "Description": "Обычная, но надёжная кирка. Хорошо подходит для добычи руды и минералов."
      },
      "bur_t0k6": {
        "Name": "Бур T0-K6",
        "TypeItem": "Оружие",
        "Quality": "Мистическое",
        "Description": "Мощный бур, разработанный для быстрой и глубокой добычи. Намного эффективнее кирки, особенно против твёрдых пород."
      },
      "material_slime_acid": {
        "Name": "Кислота слайма",
        "TypeItem": "Материал",
        "Quality": "Обычное",
        "Description": "Едкая жидкость, выделяемая слаймами. Используется для растворения минералов, таких как кварцит."
      },
      "material_quartzite": {
        "Name": "Кварцит",
        "TypeItem": "Материал",
        "Quality": "Обычное",
        "Description": "Твёрдый минерал, который можно растворить кислотой слайма, чтобы получить кварцевый песок."
      },
      "material_quartz_sand": {
        "Name": "Кварцевый песок",
        "TypeItem": "Материал",
        "Quality": "Обычное",
        "Description": "Мелкий песок, получаемый из кварцита. Подходит для выплавки прочного и чистого стекла."
      },
      "material_iron_ore": {
        "Name": "Железная руда",
        "TypeItem": "Материал",
        "Quality": "Обычное",
        "Description": "Тяжёлая и плотная руда, из которой можно выплавить железные слитки."
      },
      "staff_forest": {
        "Name": "Лесной Посох",
        "TypeItem": "Посох",
        "Quality": "Редкий",
        "Description": "Магический посох, наполненный силой леса. Его удары вызывают всплеск природной энергии, подчиняя врагов воле природы."
      },
      "trap_foottrap": {
        "Name": "Контакт-ловушка",
        "TypeItem": "Ловушка",
        "Quality": "Необычное",
        "Description": "Активируется при касании с поверхностью. Надёжно блокирует движение наземных целей — от живых существ до машин и механизмов."
      },
      "item_force_air": {
        "Name": "Эссенция полёта",
        "TypeItem": "Расходник",
        "Quality": "Необычное",
        "Description": "Сосуд с запечатанной энергией полёта. При активации высвобождает мощный импульс, на мгновение подбрасывая или отталкивая владельца."
      },
      "material_beetle_shell": {
        "Name": "Панцирь жука",
        "TypeItem": "Материал",
        "Quality": "Необычное",
        "Description": "Крепкий и гладкий фрагмент панциря, добытый с Черепокрута и Полевика. Пока не нашёл применения, но выглядит многообещающе."
      },
      "material_beetle_sludge": {
        "Name": "Жучья слизь",
        "TypeItem": "Материал",
        "Quality": "Обычное",
        "Description": "Липкая субстанция, остающаяся после волшебных жуков. Используется как органический клей в контактных ловушках."
      },
      "seed_sunflower": {
        "Name": "Семя Подсолнуха",
        "TypeItem": "",
        "Quality": "",
        "Description": "Семя яркого подсолнуха. Используется в алхимии и садоводстве."
      },
      "seed_tallsha": {
        "Name": "Семя Тальши",
        "TypeItem": "",
        "Quality": "",
        "Description": "Семя растения Тальши. Быстро растёт и используется в ремёслах и алхимии."
      },
      "seed_tonalia": {
        "Name": "Семя Тоналии",
        "TypeItem": "",
        "Quality": "",
        "Description": "Семя изящного цветка Тонилия. Ценится за его магические лепестки."
      },
      "material_tolania_leaves": {
        "Name": "Листья Толании",
        "TypeItem": "",
        "Quality": "",
        "Description": "Ароматные листья редкого растения Толания. Используются в алхимии и медицине."
      },
      "material_tallsha": {
        "Name": "Тальша",
        "TypeItem": "",
        "Quality": "",
        "Description": "Высокое густое растение, напоминающее хабку. Часто применяется в зелеварении и ремёслах."
      },
      "item_potion_mana": {
        "Name": "Зелье маны",
        "TypeItem": "Зелье",
        "Quality": "Необычное",
        "Description": "Мутная сине-фиолетовая жидкость, концентрат магической энергии. Восстанавливает ману при использовании."
      },
      "item_moonana": {
        "Name": "Бананолун",
        "TypeItem": "Еда",
        "Quality": "Необычное",
        "Description": "Редкий лунный плод, светящийся в темноте. Сладкий, восстанавливает здоровье и немного магической энергии."
      },
      "item_pepper": {
        "Name": "Жгучий перец",
        "TypeItem": "Еда",
        "Quality": "Обычное",
        "Description": "Маленький, но очень острый. Используется в кулинарии и алхимии для приготовления усиленных блюд."
      },
      "item_spicy_meat": {
        "Name": "Острое мясо",
        "TypeItem": "Еда",
        "Quality": "Необычное",
        "Description": "Блюдо из мяса, перца и тальшы. Заряжает энергией, отлично восстанавливает здоровье и разогревает изнутри."
      },
      "minion_gunmin_tech": {
        "Name": "Техно-смоловой миньон",
        "TypeItem": "",
        "Quality": "",
        "Description": "Этот миньон атакует врагов и кратковременно их обездвиживает."
      },
      "minion_heal": {
        "Name": "Целительный миньон",
        "TypeItem": "",
        "Quality": "",
        "Description": "Этот миньон лечит игрока, восстанавливая его здоровье в бою."
      },
      "lazergun_tra": {
        "Name": "Лазер-TRA2000",
        "TypeItem": "Оружие",
        "Quality": "Легендарное",
        "Description": "Флагманское оружие серии TRA. Генерирует мощный сквозной лазерный луч, испаряющий врагов за доли секунды. Надёжность, мощь и стиль в одном корпусе."
      },
      "thunder_gun": {
        "Name": "Молниемёт",
        "TypeItem": "Оружие",
        "Quality": "Мистическое",
        "Description": "Пушка, стреляющая цепными молниями, отскакивающими от врага к врагу. Идеальна для борьбы с группами целей — электричество найдёт путь."
      },
      "thunder_stuff": {
        "Name": "Грозовой Посох",
        "TypeItem": "Оружие",
        "Quality": "Мистическое",
        "Description": "Магический посох, стреляющий цепными молниями, отскакивающими от врага к врагу. Требует ману для использования и идеально подходит для ведения боя с группами противников."
      },
      "material_book": {
        "Name": "Книга знаний",
        "TypeItem": "Материал",
        "Quality": "Обычное",
        "Description": "Обычная книга с базовыми записями. Используется в ремесле и исследованиях."
      },
      "booster_intelligence": {
        "Name": "Том интеллекта",
        "TypeItem": "Материал",
        "Quality": "Редкое",
        "Description": "Древний том с магическими символами. Повышает интеллект на 2 единицы при использовании."
      },
      "material_syringe": {
        "Name": "Пустой шприц",
        "TypeItem": "Материал",
        "Quality": "Обычное",
        "Description": "Стандартный стерильный шприц. Используется в создании различных усиливающих препаратов."
      },
      "booster_strength": {
        "Name": "Усиляющий шприц силы",
        "TypeItem": "Материал",
        "Quality": "Редкое",
        "Description": "Шприц с концентрированным стимулятором. Повышает силу на 2 единицы."
      },
      "booster_agillity": {
        "Name": "Усиляющий шприц ловкости",
        "TypeItem": "Материал",
        "Quality": "Редкое",
        "Description": "Шприц с быстродействующим препаратом. Повышает ловкость на 2 единицы."
      }
    },
    "mobs": {
      "daizen_enem": {
        "Name": "Дайзер",
        "TypeMob": "",
        "Description": "Простой моб с ближней аттакой"
      },
      "rainger_enem": {
        "Name": "Райнгер",
        "TypeMob": "",
        "Description": "Простой моб с дальной аттакой"
      },
      "slime_enem": {
        "Name": "Слизень",
        "TypeMob": "",
        "Description": "Средний слизень"
      },
      "slime_boss_enem": {
        "Name": "Большой чертов слизень",
        "TypeMob": "",
        "Description": "Этот чертов слизень большой, без шуток!"
      },
      "mimic_enem": {
        "Name": "Сундук мимик",
        "TypeMob": "",
        "Description": "Быстрый и опасный сундук"
      },
      "death_car_enem": {
        "Name": "Машина-убийца",
        "TypeMob": "",
        "Description": "Роботизированная машина с циркулярной пилой, созданная истреблять всё живое на своём пути"
      },
      "tasty_fly_enem": {
        "Name": "Обжирокрыл",
        "TypeMob": "",
        "Description": "Зелёное крылатое существо, представляющее собой один большой рот с отличным чутьём. Обожает пожирать всё, что попадётся на пути."
      },
      "bur_enem": {
        "Name": "Пещеродёр",
        "TypeMob": "",
        "Description": "Неумолимая бурильная машина, созданная для тоннелей, разрывающая камень и плоть на своём бесконечном пути сквозь пещеры."
      },
      "bug_skull_enem": {
        "Name": "Черепокрут",
        "TypeMob": "",
        "Description": "Необычный жук из магического мира, катающий гигантский череп древнего титана. Использует его как смертоносное оружие, запуская во врагов с сокрушительной силой."
      },
      "bug_enem": {
        "Name": "Полевик",
        "TypeMob": "",
        "Description": "Малый, но стремительный жук из волшебных земель. Без своего шара он просто несётся вперёд, пытаясь сбить врага напором."
      }
    },
    "ui_text": {
      "player_stats_name": {
        "word_status_info": "Статус",
        "word_Cur_Hp": "Текущее HP",
        "word_Max_Hp": "Макс. HP",
        "word_Max_Mana": "Макс. Мана",
        "word_Mana": "Mаны",
        "word_Mana_Regen": "К регенерации маны",
        "word_Armor_Hp": "Броня",
        "word_Mov_Speed": "Скорость",
        "word_Att_Range": "К дальности атаки",
        "word_Att_Damage": "К урону",
        "word_Att_Speed": "К скорости атаки",
        "word_Proj_Speed": "К скорости снарядов",
        "word_level": "Уровень",
        "word_freeSkillPoints": "Свободные очки обучения",
        "word_cur_exp": "Текущий опыт",
        "word_nextLvl_exp": "до след. уровня",
        "word_classPlayer": "Класс игрока",
        "word_curse_lvl": "Уровень проклятья",
        "word_char_lvl": "Уровень зачарования",
        "word_art_lvl": "Уровень артефакта",
        "word_Damage": "Урона",
        "word_Armor": "Брони",
        "word_Speed": "Скорость",
        "word_Evasion": "К уклонению",
        "word_AttSpeed": "Скорость атаки",
        "word_AttRange": "Дальность атаки",
        "word_ProjSpeed": "Скорость снаряда",
        "word_eqipment": "снаряж",
        "word_roleClass": "класс",
        "word_strength": "сила",
        "word_agility": "ловк.",
        "word_intelligence": "интел.",
        "word_expBonus": "бонус к опыту",
        "word_base": "баз. знач.",
        "word_for": "от ",
        "word_TradeSkill": "Уровень обмена",
        "word_gold": "Золото",
        "word_technology_gold": "Знания технологий",
        "word_mage_gold": "Знания магии",
        "word_count_proj": "Доп. снаряды",
        "word_Tech_Resis": "сопр. технол.",
        "word_Magic_Resis": "сопр. магии",
        "word_trade_skill": "Торговля",
        "word_farm_skill": "Фермерство",
        "word_collect_skill": "Сбор",
        "word_experience": "опыт",
        "word_exp_to_next_level": "опыта до нового уровня"
      },
      "slots_name": {
        "word_player": "игрока",
        "word_typeItem": "Тип предмета",
        "word_damageType": "Тип урона",
        "word_damage": "Урона за атаку",
        "word_attacks_speed": "Скорость атаки",
        "word_attacks_intervals": "Атак в секунду",
        "word_range": "Дальность",
        "word_manaCost": "Маны за использование",
        "word_description": "Описание"
      },
      "shop_text": {
        "word_gold": "золота",
        "word_not_enough_money": "Недостаточно золота",
        "word_total_value": "Общая ценность: ",
        "word_personal_cost": "Персональная стоимость: ",
        "word_trade_without_gold": "Торговля без золота",
        "word_must_pay": "Вы должны заплатить",
        "word_will_receive": "Вы получите",
        "word_your_gold": "Ваше золото: ",
        "word_your_trade_skill": "Ваш торговый навык: ",
        "word_cost": "Цена: ",
        "word_trade_success": "Успешная сделка",
        "word_player": "Игрок",
        "word_trader": "Торговец",
        "word_trade_name": "Торговля"
      },
      "aspects_name": {
        "word_nameWindow": "Выбери улучшение",
        "word_acceptButton": "Выбрать",
        "word_Agillity": "к ловкости",
        "word_Strength": "к силе",
        "word_Intelligence": "к интеллекту",
        "word_Tech_Point": "к очкам технологий",
        "word_Mage_Point": "к очкам магии",
        "word_Exp_Bust": "к бонусу опыта",
        "word_Speed": "к скорости",
        "word_Hp": "к очкам здоровья",
        "word_Mana": "к очкам маны",
        "word_Mana_Regen": "к регенерации маны",
        "word_Gold": "к золоту",
        "word_AttackSpeed": "к скорости атаки",
        "word_Range": "к дальности",
        "word_Projectile_speed": "к скорости снаряда",
        "word_Damage": "к урону"
      },
      "name_location": {
        "Game_village": "Деревня Тонио почти-мудрого",
        "Level_one": "Уровень №1 — Поле слегка разъярённых овец",
        "Level_two": "Уровень №2 — Пещера Тенеклыка"
      }
    }
  }
}